explicit/kafka/__init__.py
explicit/kafka/py.typed
explicit/kafka/adapters/__init__.py
explicit/kafka/adapters/messaging.py
explicit/kafka/domain/__init__.py
explicit/kafka/domain/model/__init__.py
explicit/kafka/domain/model/auth.py
explicit/kafka/domain/model/config.py
explicit_kafka-1.1.0.dist-info/METADATA
explicit_kafka-1.1.0.dist-info/WHEEL
explicit_kafka-1.1.0.dist-info/dependency_links.txt
explicit_kafka-1.1.0.dist-info/top_level.txt
explicit_kafka-1.1.0.dist-info/RECORD
