Metadata-Version: 2.1
Name: explicit-kafka
Version: 1.1.0
Summary: Набор компонентов для интеграции explicit с kafka
Author: BARS Group
Author-email: education_dev@bars-open.ru
License: MIT
Classifier: Intended Audience :: Developers
Classifier: Environment :: Web Environment
Classifier: Natural Language :: Russian
Classifier: Operating System :: OS Independent
Classifier: Programming Language :: Python
Classifier: Programming Language :: Python :: 3.9
Classifier: Programming Language :: Python :: 3.10
Classifier: Programming Language :: Python :: 3.11
Classifier: Programming Language :: Python :: 3.12
Classifier: Development Status :: 5 - Production/Stable
Requires-Dist: explicit <3,>=2
Requires-Dist: confluent-kafka
